finbert_embedding/__init__.py
finbert_embedding/downloader.py
finbert_embedding/embedding.py
finbert_embedding-0.1.5.dist-info/LICENSE
finbert_embedding-0.1.5.dist-info/METADATA
finbert_embedding-0.1.5.dist-info/WHEEL
finbert_embedding-0.1.5.dist-info/top_level.txt
finbert_embedding-0.1.5.dist-info/RECORD
