Metadata-Version: 2.1
Name: finbert-embedding
Version: 0.1.5
Summary: Embeddings from Financial BERT
Home-page: https://github.com/abhijeet3922/finbert_embedding
Author: Abhijeet Kumar
Author-email: abhijeetchar@gmail.com
License: UNKNOWN
Download-URL: https://github.com/abhijeet3922/finbert_embedding/archive/v0.1.4.tar.gz
Platform: UNKNOWN
Classifier: Programming Language :: Python :: 3
Classifier: License :: OSI Approved :: MIT License
Classifier: Operating System :: OS Independent
Requires-Python: >=3.6
Requires-Dist: torch (>=1.1.0)
Requires-Dist: pytorch-pretrained-bert (==0.6.2)
Requires-Dist: tensorflow
